appswag/__init__.py
appswag/core.py
appswag/errs.py
appswag/getter.py
appswag/io.py
appswag/resolve.py
appswag/scan.py
appswag/utils.py
appswag/consts/__init__.py
appswag/consts/private.py
appswag/contrib/__init__.py
appswag/contrib/client/__init__.py
appswag/contrib/client/flask.py
appswag/contrib/client/requests.py
appswag/contrib/client/tornado.py
appswag/contrib/client/webapp2.py
appswag/primitives/__init__.py
appswag/primitives/_array.py
appswag/primitives/_bool.py
appswag/primitives/_byte.py
appswag/primitives/_file.py
appswag/primitives/_float.py
appswag/primitives/_int.py
appswag/primitives/_model.py
appswag/primitives/_str.py
appswag/primitives/_time.py
appswag/primitives/_uuid.py
appswag/primitives/codec.py
appswag/primitives/comm.py
appswag/primitives/render.py
appswag/scanner/__init__.py
appswag/scanner/cycle_detector.py
appswag/scanner/type_reducer.py
appswag/scanner/v1_2/__init__.py
appswag/scanner/v1_2/upgrade.py
appswag/scanner/v1_2/validate.py
appswag/scanner/v2_0/__init__.py
appswag/scanner/v2_0/aggt.py
appswag/scanner/v2_0/assign_parent.py
appswag/scanner/v2_0/merge.py
appswag/scanner/v2_0/norm_ref.py
appswag/scanner/v2_0/patch_obj.py
appswag/scanner/v2_0/resolve.py
appswag/scanner/v2_0/validate.py
appswag/scanner/v2_0/yaml.py
appswag/spec/__init__.py
appswag/spec/base.py
appswag/spec/v1_2/__init__.py
appswag/spec/v1_2/objects.py
appswag/spec/v1_2/parser.py
appswag/spec/v2_0/__init__.py
appswag/spec/v2_0/objects.py
appswag/spec/v2_0/parser.py
appswag/tests/__init__.py
appswag/tests/test_base.py
appswag/tests/test_codec.py
appswag/tests/test_core.py
appswag/tests/test_getter.py
appswag/tests/test_render.py
appswag/tests/test_utils.py
appswag/tests/test_yaml.py
appswag/tests/utils.py
appswag-0.10.0.dist-info/LICENSE
appswag-0.10.0.dist-info/METADATA
appswag-0.10.0.dist-info/WHEEL
appswag-0.10.0.dist-info/top_level.txt
appswag-0.10.0.dist-info/RECORD
